gpapi/__init__.py
gpapi/config.py
gpapi/device.properties
gpapi/googleplay.py
gpapi/googleplay_pb2.py
gpapi/utils.py
vgpapi-0.4.3.5.dist-info/METADATA
vgpapi-0.4.3.5.dist-info/RECORD
vgpapi-0.4.3.5.dist-info/WHEEL
vgpapi-0.4.3.5.dist-info/top_level.txt
